NectarGraphix/main.py
NectarGraphix/background/Nectar Splash.png
NectarGraphix/background/NectarX.ico
NectarGraphix/background/NectarX.jpeg
NectarGraphix/background/NectarX.png
NectarGraphix/background/close.png
NectarGraphix/background/default.png
NectarGraphix/background/desktop.ini
NectarGraphix/background/down-arrow.svg
NectarGraphix/background/easel.ico
NectarGraphix/background/easel.png
NectarGraphix/background/explore.png
NectarGraphix/background/halfpic.jpg
NectarGraphix/background/icon3.ico
NectarGraphix/background/icon3.png
NectarGraphix/background/image.png
NectarGraphix/background/image2.png
NectarGraphix/background/main.png
NectarGraphix/background/max.jpg
NectarGraphix/background/max5.jpg
NectarGraphix/background/mic.png
NectarGraphix/background/mini.png
NectarGraphix/background/on.png
NectarGraphix/background/plug.png
NectarGraphix/background/refresh.png
NectarGraphix/background/settings.png
NectarGraphix/background/speech.png
NectarGraphix/background/store.png
NectarGraphix/background/tray.png
NectarGraphix/background/update.png
nectargraphix-0.1.7.dist-info/licenses/LICENSE
nectargraphix-0.1.7.dist-info/METADATA
nectargraphix-0.1.7.dist-info/WHEEL
nectargraphix-0.1.7.dist-info/entry_points.txt
nectargraphix-0.1.7.dist-info/top_level.txt
nectargraphix-0.1.7.dist-info/RECORD
