Metadata-Version: 2.4
Name: NectarGraphix
Version: 0.1.7
Summary: Image generation studio
Author-email: Headlessripper <zashiron.inc@gmail.com>
License: Nectar-X-Studio Proprietary License (Zashiron License v1.2)
Project-URL: Homepage, https://github.com/headlessripper/Nectar-X-Studio
License-File: LICENSE
Requires-Dist: PyQt6
Requires-Dist: requests
Requires-Dist: huggingface_hub
Requires-Dist: numpy
Requires-Dist: tensorboard
Requires-Dist: transformers
Requires-Dist: diffusers
Requires-Dist: Pillow
Requires-Dist: PyQt6-WebEngine
Requires-Dist: torch
Dynamic: license-file
